bpfeeder/__init__.py
bpfeeder/cybos.py
bpfeeder/feeder.py
bpfeeder/investing.py
bpfeeder/naver.py
bpfeeder/symbol.py
bpfeeder/utils.py
bpfeeder/yahoo.py
bpfeeder-0.0.3.dist-info/METADATA
bpfeeder-0.0.3.dist-info/WHEEL
bpfeeder-0.0.3.dist-info/top_level.txt
bpfeeder-0.0.3.dist-info/RECORD
